cgs_cli/main.py
cgs_cli/messages.py
cgs_cli/terraform/main.tf
cgs_cli-0.3.0.dist-info/licenses/LICENSE
cgs_cli-0.3.0.dist-info/METADATA
cgs_cli-0.3.0.dist-info/WHEEL
cgs_cli-0.3.0.dist-info/entry_points.txt
cgs_cli-0.3.0.dist-info/top_level.txt
cgs_cli-0.3.0.dist-info/RECORD
