Metadata-Version: 2.4
Name: cgs-cli
Version: 0.3.0
Summary: A CLI tool to deploy your game server to the cloud with a single command.
Author-email: rosmontisu <rosmontisu@gmail.com>
License-Expression: MIT
Project-URL: Homepage, https://github.com/rosmontisu/cloud-game-starter
Project-URL: Bug Tracker, https://github.com/rosmontisu/cloud-game-starter/issues
Classifier: Programming Language :: Python :: 3
Classifier: Operating System :: OS Independent
Requires-Python: >=3.8
License-File: LICENSE
Requires-Dist: typer[all]
Dynamic: license-file
